aionewton/__init__.py
aionewton/extensions.py
aionewton/wrapper.py
aionewton-1.0.6.dist-info/METADATA
aionewton-1.0.6.dist-info/RECORD
aionewton-1.0.6.dist-info/WHEEL
aionewton-1.0.6.dist-info/top_level.txt
