Metadata-Version: 2.1
Name: aionewton
Version: 1.0.6
Summary: An asyncio-based wrapper for the newton-api
Home-page: https://github.com/ilevn/aionewton
Author: Nils Theres
Author-email: nilsntth@gmail.com
License: MIT
Platform: UNKNOWN
Requires-Dist: aiohttp (>=2.0.5)
